edgedb_dto/__init__.py
edgedb_dto/cli.py
edgedb_dto/config.py
edgedb_dto/dto.py
edgedb_dto/generator.py
edgedb_dto/utils.py
edgedb_dto-1.0.2.dist-info/LICENSE
edgedb_dto-1.0.2.dist-info/METADATA
edgedb_dto-1.0.2.dist-info/WHEEL
edgedb_dto-1.0.2.dist-info/entry_points.txt
edgedb_dto-1.0.2.dist-info/RECORD
