Metadata-Version: 2.1
Name: edgedb-dto
Version: 1.0.2
Summary: Edgedb DTO is a library that generates DTO pydantic dataclasses from edgeql files.
Author: Mohamed Sahnoun
Author-email: mohammed.sahnounn@gmail.com
Requires-Python: >=3.11,<4.0
Classifier: Programming Language :: Python :: 3
Classifier: Programming Language :: Python :: 3.11
Classifier: Programming Language :: Python :: 3.12
Requires-Dist: black (>=24.4.2,<25.0.0)
Requires-Dist: edgedb (>=1.9.0,<2.0.0)
Requires-Dist: jinja2 (>=3.1.4,<4.0.0)
Requires-Dist: pydantic (>=2.7.3,<3.0.0)
